beamline/__init__.py
beamline/blparser.py
beamline/datautils.py
beamline/element.py
beamline/elements.py
beamline/lattice.py
beamline/matchutils.py
beamline/mathutils.py
beamline/models.py
beamline/pltutils.py
beamline/simulation.py
beamline/ui/__init__.py
beamline/ui/appui.py
beamline/ui/main.py
beamline/ui/myappframe.py
beamline/ui/mychoiceframe.py
beamline/ui/mydataframe.py
beamline/ui/mydrawframe.py
beamline/ui/mylogframe.py
beamline/ui/pltutils.py
beamline-1.3.5.2.data/scripts/file2lower.sh
beamline-1.3.5.2.data/scripts/json2lte
beamline-1.3.5.2.data/scripts/latticeviewer
beamline-1.3.5.2.data/scripts/lte2json
beamline-1.3.5.2.data/scripts/lv
beamline-1.3.5.2.data/scripts/renametolower.sh
beamline-1.3.5.2.data/scripts/runElegant.sh
beamline-1.3.5.2.data/scripts/sddsprintdata.sh
beamline-1.3.5.2.dist-info/DESCRIPTION.rst
beamline-1.3.5.2.dist-info/METADATA
beamline-1.3.5.2.dist-info/RECORD
beamline-1.3.5.2.dist-info/WHEEL
beamline-1.3.5.2.dist-info/metadata.json
beamline-1.3.5.2.dist-info/top_level.txt
