Metadata-Version: 2.0
Name: beamline
Version: 1.3.5.2
Summary: online model package for electron accelerator
Home-page: http://archman.github.io/beamline/
Author: Tong Zhang
Author-email: warriorlance@gmail.com
License: MIT
Platform: Linux
Requires: pyrpn
Requires: h5py
Requires: numpy
Requires: matplotlib
Requires: pyepics
